youtube_auto_publish/__init__.py
youtube_auto_publish-0.1.5.dist-info/LICENSE
youtube_auto_publish-0.1.5.dist-info/METADATA
youtube_auto_publish-0.1.5.dist-info/WHEEL
youtube_auto_publish-0.1.5.dist-info/top_level.txt
youtube_auto_publish-0.1.5.dist-info/RECORD
