Metadata-Version: 2.1
Name: youtube-auto-publish
Version: 0.1.5
Author-email: Lucas Gasque <lucasfdg@hotmail.com>
Project-URL: Homepage, https://github.com/top-5-twitch/youtube-auto-publish
Project-URL: Issues, https://github.com/top-5-twitch/youtube-auto-publish/issues
Requires-Python: >=3.12
License-File: LICENSE
Requires-Dist: selenium >=4.22.0
Provides-Extra: test
Requires-Dist: pytest >=8.3.2 ; extra == 'test'
Requires-Dist: pytest-cov >=5.0.0 ; extra == 'test'
Requires-Dist: pytest-asyncio >=0.23.8 ; extra == 'test'
Requires-Dist: ruff >=0.5.7 ; extra == 'test'
